{"frames":{"sprite1":{"frame":{"x":0,"y":0,"w":250,"h":400},"rotated":false,"trimmed":false,"spriteSourceSize":{"x":0,"y":0,"w":250,"h":400},"sourceSize":{"w":250,"h":400}},"sprite2":{"frame":{"x":250,"y":0,"w":250,"h":400},"rotated":false,"trimmed":false,"spriteSourceSize":{"x":0,"y":0,"w":250,"h":400},"sourceSize":{"w":250,"h":400}},"sprite3":{"frame":{"x":500,"y":0,"w":250,"h":400},"rotated":false,"trimmed":false,"spriteSourceSize":{"x":0,"y":0,"w":250,"h":400},"sourceSize":{"w":250,"h":400}},"sprite4":{"frame":{"x":750,"y":0,"w":250,"h":400},"rotated":false,"trimmed":false,"spriteSourceSize":{"x":0,"y":0,"w":250,"h":400},"sourceSize":{"w":250,"h":400}},"sprite5":{"frame":{"x":1000,"y":0,"w":250,"h":400},"rotated":false,"trimmed":false,"spriteSourceSize":{"x":0,"y":0,"w":250,"h":400},"sourceSize":{"w":250,"h":400}},"sprite6":{"frame":{"x":1250,"y":0,"w":250,"h":400},"rotated":false,"trimmed":false,"spriteSourceSize":{"x":0,"y":0,"w":250,"h":400},"sourceSize":{"w":250,"h":400}},"sprite7":{"frame":{"x":1500,"y":0,"w":250,"h":400},"rotated":false,"trimmed":false,"spriteSourceSize":{"x":0,"y":0,"w":250,"h":400},"sourceSize":{"w":250,"h":400}},"sprite8":{"frame":{"x":1750,"y":0,"w":250,"h":400},"rotated":false,"trimmed":false,"spriteSourceSize":{"x":0,"y":0,"w":250,"h":400},"sourceSize":{"w":250,"h":400}},"sprite9":{"frame":{"x":2000,"y":0,"w":250,"h":400},"rotated":false,"trimmed":false,"spriteSourceSize":{"x":0,"y":0,"w":250,"h":400},"sourceSize":{"w":250,"h":400}}},"meta":{"app":"https://www.leshylabs.com/apps/sstool/","version":"Leshy SpriteSheet Tool v0.8.4","image":"spritesheet.png","size":{"w":2250,"h":400},"scale":1}}